sliceable_generator/__init__.py
sliceable_generator-0.1.2.dist-info/LICENSE
sliceable_generator-0.1.2.dist-info/METADATA
sliceable_generator-0.1.2.dist-info/WHEEL
sliceable_generator-0.1.2.dist-info/top_level.txt
sliceable_generator-0.1.2.dist-info/RECORD
