Metadata-Version: 2.1
Name: sliceable-generator
Version: 0.1.2
Summary: Sliceable subscriptable reusable generator.
Home-page: https://github.com/panhaoyu/sliceable-generator
Author: panhaoyu
Author-email: panhaoyu.china@outlook.com
License: UNKNOWN
Platform: UNKNOWN
Classifier: Programming Language :: Python :: 3
Classifier: License :: OSI Approved :: MIT License
Classifier: Operating System :: OS Independent
Requires-Python: >=3.6
